pypass/__init__.py
pypass/main.py
pypass/app/__init__.py
pypass/app/cli/__init__.py
pypass/app/cli/pypass_cli.py
pypass/app/gui/__init__.py
pypass/app/gui/desktop/__init__.py
pypass/app/gui/desktop/pypass_gui.py
pypass/app/gui/web/__init__.py
pypass/app/gui/web/content.py
pypass/app/gui/web/pypass_web.py
pypass/database/__init__.py
pypass/database/connect.py
pypass/passwords/__init__.py
pypass/passwords/infos.md
pypass_tool-0.3.1.dist-info/LICENSE.md
pypass_tool-0.3.1.dist-info/METADATA
pypass_tool-0.3.1.dist-info/WHEEL
pypass_tool-0.3.1.dist-info/entry_points.txt
pypass_tool-0.3.1.dist-info/top_level.txt
pypass_tool-0.3.1.dist-info/RECORD
