Metadata-Version: 2.1
Name: pypass-tool
Version: 0.3.1
Summary: A CLI tool for password generation
Home-page: https://github.com/h471x/password_generator
Author: Hatix Ntsoa
Author-email: hatixntsoa@gmail.com
License: MIT
Classifier: Programming Language :: Python :: 3
Classifier: License :: OSI Approved :: MIT License
Classifier: Operating System :: OS Independent
License-File: LICENSE.md
Requires-Dist: Flask
Requires-Dist: pyperclip
Requires-Dist: setuptools
